sugar/__init__.py
sugar/atom.py
sugar/bond.py
sugar/cube.py
sugar/forcefield_assign.py
sugar/mol_database.py
sugar/molecule.py
sugar/monte_carlo.py
sugar/trajectory_analysis.py
sugar/utilities.py
sugar/voronoi_diagram.py
sugar/extra_func/__init__.py
sugar/extra_func/extra_functions.py
sugar/extra_func/gaussian_output.py
sugar/forcefield/__init__.py
sugar/forcefield/amber_parameters.py
sugar/forcefield/obabel_parameter_assign.py
sugar/forcefield/potential.py
sugar/forcefield/uff4mof_parameter.py
sugar/forcefield/uff4mof_parameter_assign.py
sugar/forcefield/uff_parameter.py
sugar/pywindow/__init__.py
sugar/pywindow/io_tools.py
sugar/pywindow/molecular.py
sugar/pywindow/tables.py
sugar/pywindow/trajectory.py
sugar/pywindow/utilities.py
supramolecular_sugar-0.5.dist-info/LICENSE.md
supramolecular_sugar-0.5.dist-info/METADATA
supramolecular_sugar-0.5.dist-info/WHEEL
supramolecular_sugar-0.5.dist-info/top_level.txt
supramolecular_sugar-0.5.dist-info/RECORD
