Metadata-Version: 2.1
Name: supramolecular-sugar
Version: 0.5
Summary: SUpramolecular recoGnition prediction in porous moleculAR materials
Home-page: https://github.com/Chemwzd/sugar
Author: Zidi Wang
Author-email: 
Classifier: Programming Language :: Python :: 3
Classifier: License :: OSI Approved :: MIT License
Classifier: Operating System :: OS Independent
Requires-Python: >=3.8
License-File: LICENSE.md
Requires-Dist: networkx
Requires-Dist: matplotlib
Requires-Dist: rdkit-pypi (==2022.3.5)
Requires-Dist: numpy (==1.22.4)
Requires-Dist: scipy (==1.7.1)
Requires-Dist: MDAnalysis (==2.4.3)
Requires-Dist: pyvoro (==1.3.2)
